pydoover/__init__.py
pydoover/cli/__init__.py
pydoover/cli/cli.py
pydoover/cli/decorators.py
pydoover/cli/parsers.py
pydoover/cli/sub_section.py
pydoover/cloud/__init__.py
pydoover/cloud/api/__init__.py
pydoover/cloud/api/agent.py
pydoover/cloud/api/application.py
pydoover/cloud/api/channel.py
pydoover/cloud/api/client.py
pydoover/cloud/api/config.py
pydoover/cloud/api/exceptions.py
pydoover/cloud/api/message.py
pydoover/cloud/api/object.py
pydoover/cloud/processor/__init__.py
pydoover/cloud/processor/base.py
pydoover/config/__init__.py
pydoover/docker/__init__.py
pydoover/docker/application.py
pydoover/docker/grpc_generate.bash
pydoover/docker/grpc_interface.py
pydoover/docker/device_agent/__init__.py
pydoover/docker/device_agent/device_agent.proto
pydoover/docker/device_agent/device_agent.py
pydoover/docker/device_agent/grpc_generate.bash
pydoover/docker/device_agent/grpc_stubs/__init__.py
pydoover/docker/device_agent/grpc_stubs/device_agent_pb2.py
pydoover/docker/device_agent/grpc_stubs/device_agent_pb2.pyi
pydoover/docker/device_agent/grpc_stubs/device_agent_pb2_grpc.py
pydoover/docker/modbus/__init__.py
pydoover/docker/modbus/config.py
pydoover/docker/modbus/grpc_generate.bash
pydoover/docker/modbus/modbus_iface.proto
pydoover/docker/modbus/modbus_iface.py
pydoover/docker/modbus/grpc_stubs/__init__.py
pydoover/docker/modbus/grpc_stubs/modbus_iface_pb2.py
pydoover/docker/modbus/grpc_stubs/modbus_iface_pb2.pyi
pydoover/docker/modbus/grpc_stubs/modbus_iface_pb2_grpc.py
pydoover/docker/platform/__init__.py
pydoover/docker/platform/grpc_generate.bash
pydoover/docker/platform/platform.py
pydoover/docker/platform/platform_iface.proto
pydoover/docker/platform/platform_types.py
pydoover/docker/platform/grpc_stubs/__init__.py
pydoover/docker/platform/grpc_stubs/platform_iface_pb2.py
pydoover/docker/platform/grpc_stubs/platform_iface_pb2.pyi
pydoover/docker/platform/grpc_stubs/platform_iface_pb2_grpc.py
pydoover/reports/__init__.py
pydoover/reports/base.py
pydoover-0.4.18.dist-info/METADATA
pydoover-0.4.18.dist-info/WHEEL
pydoover-0.4.18.dist-info/entry_points.txt
pydoover-0.4.18.dist-info/licenses/LICENSE
pydoover-0.4.18.dist-info/RECORD
